{"cameraMode":{"drawMode":0,"name":"Shaded","section":"Shading Mode"},"sceneLighting":true,"audioPlay":false,"sceneViewState":{"m_AlwaysRefresh":false,"showFog":true,"showSkybox":true,"showFlares":true,"showImageEffects":true,"showParticleSystems":true,"showVisualEffectGraphs":true,"m_FxEnabled":true},"in2DMode":false,"pivot":{"x":2.7225217819213869,"y":1.9671404361724854,"z":0.14580067992210389},"rotation":{"x":-0.15498313307762147,"y":0.7917430400848389,"z":-0.2245091050863266,"w":-0.5465553998947144},"size":1.7762675285339356,"orthographic":false}